{"jHdYNS/oCtbVREzDJGwR7w==":"banner-bg-2000x465.jpg","bXRRBeul0AF+7u/+Ww3m5w==":"img-2-1114x945.png","QLo8KPIab7VQqcn7vL/NIw==":"faydalari-655x800.png","txH50GIVuy/pSiWdQJU8Hw==":"%d9%a1%d9%a0-310x474.jpg","KqRJtyAcb4VtcULK7G5mwg==":"1-310x435.png","YlHBqcQuY7tGnKiu0or+MQ==":"2-310x437.png","fydWtWJsRpRDAoG1cM6nSA==":"3-310x438.png","srVKDAjzouKQ2GftjGWDGw==":"6-310x439.png","ffYoTF2qrbpoAc9QuvSmsA==":"7-310x438.png","HcrHjZZteDdOuS1Sl+pUMQ==":"8-310x442.png","JHaHGagQG56JAcCfwvjE0Q==":"9-310x437.png","6ixWx0hcF/ZntV9Dd5KR9g==":"10-310x436.png","hhZYzFvIoodbF/gb4oCkmg==":"11-310x435.png","KulZIQ9l9bLiNfsL0JaaIg==":"1-583x819.png","K1lgXeTf+EiwddEY5HUoMg==":"2-583x822.png","VXwPkYbOEvoXeQ9Jd2x9Nw==":"3-580x819.png","DnYtEKgwKJnzpLK7uItIgg==":"4-563x795.png","i8+b81RFg6UiEOTh+Tc6pQ==":"5-584x822.png","Ojpf7WWIgY4r9ixUA9wOuw==":"6-580x821.png","+PtvAAv5ZHC4nYsy9XIU8A==":"7-584x825.png","N4QU6Auluaa5xxScC2BNwA==":"8-557x794.png","uvrQlw8t3fYTprN/gCHX2A==":"9-582x821.png","lD+E8n5hLRjLJb6HYioA9Q==":"10-581x818.png","dUqnsOrVfNfm7IVgCnqbNw==":"11-583x818.png","yegloi+ZICwdOava1HM8rQ==":"12-563x792.png","5HOM0y7B/JGxuMcY2Xm6wA==":"1-590x840.png","wrW/vMQtn1Bu5OYi46CByQ==":"3-590x840.png","d1WOptaiRhTyTCWYf3chsA==":"4-510x390.png","vZASpwk13IYKqF9s6d1amA==":"2-590x840.png","CSU9V0V1pYL3mwxr6OYZKA==":"logo.svg","J0Zirn2WJ2VjFLNcZDjVfA==":"new%20logo-183x64.png","0HL/e/pUXKZw4drA4v2pKA==":"new%20logo-684x239.png","kdqrb6PRLgSNLH0aw/QT8w==":"logo%20footer.svg","aVIYEXu0GvDsrIfoniTusg==":"logo%20footer.png","x4zFX5CIkfS2xtr1KXpLDw==":"logo%20footer.png","kbu0pb4lAqoQF3G9FBcA7Q==":"logo%20footer.png","SkP17B0L4UE7RWp42Be9PA==":"logo%20footer.png","md/S7yri5Ns3GHekpv+j7g==":"logo%20footer.png","ApeVjwlPInHEbRvWwBG17A==":"logo%20footer.png","tglEAwjEQYHZ5u3wqbnaWw==":"logo%20footer.png","QjxQaiudepCrEi13aeZ63g==":"logo-1.png","MUoO2sVBJggVqfaVzvpWaw==":"logo_small-80x52.png","5THWMHJSOMUiZT3WWTMKog==":"logo_small-80x80.png","wBl1mNWALkjrnHGTYDw1DA==":"logo_small1-80x80.png","4hSmZR5P8XEO61xkQEyN8w==":"logo_small-412x412.png","5d0RVhaU68Z2361PKaY5DQ==":"anasayfa-1465x650.png","QSt9R4dAKfsGtMwn9NmHGA==":"logo-removebg-preview%20(1)-137x37.png","GOhow07nP2PH37zweLLaLw==":"logo-removebg-preview%20(1)-137x37.png","5EHvp6VEYHrvnyeFCsevDw==":"logo-removebg-preview%20(1)-674x181.png","vDoIzj0MFDBOM8rWucCOkg==":"logo%20footer.svg","tWfVst5yJy2O/Vk1RwDklw==":"logo%20footer.png","myCrsC+fYQhfDe+eACRDrw==":"logo-removebg-preview-80x21.png","MWUZ89T72aAYYpLyhvhXyw==":"icon%20logo-80x66.png","/ImG517l8mG6nqeNl7iPOQ==":"logo%20footer.png","SdMyFmX21YI4HfSdb1P/XA==":"logo-removebg-preview-140x38.png"}